CHANGELOG.md
LICENSE.txt
MANIFEST.in
README.md
requirements.txt
setup.cfg
setup.py
hgijson/__init__.py
hgijson/custom_types.py
hgijson/serialization.py
hgijson/serializers.py
hgijson.egg-info/PKG-INFO
hgijson.egg-info/SOURCES.txt
hgijson.egg-info/dependency_links.txt
hgijson.egg-info/requires.txt
hgijson.egg-info/top_level.txt
hgijson/json_converters/__init__.py
hgijson/json_converters/_converters.py
hgijson/json_converters/_serialization.py
hgijson/json_converters/_serializers.py
hgijson/json_converters/automatic.py
hgijson/json_converters/builders.py
hgijson/json_converters/interfaces.py
hgijson/json_converters/models.py
hgijson/json_converters/primitive.py
hgijson/tests/__init__.py
hgijson/tests/_models.py
hgijson/tests/_serializers.py
hgijson/tests/_stubs.py
hgijson/tests/test_models.py
hgijson/tests/test_serialization.py
hgijson/tests/test_serializers.py
hgijson/tests/json_converters/__init__.py
hgijson/tests/json_converters/_helpers.py
hgijson/tests/json_converters/_serializers.py
hgijson/tests/json_converters/test_automatic.py
hgijson/tests/json_converters/test_builders.py
hgijson/tests/json_converters/test_converters.py
hgijson/tests/json_converters/test_models.py
hgijson/tests/json_converters/test_primitive.py
hgijson/tests/json_converters/test_serialization.py
hgijson/tests/json_converters/functionality/__init__.py
hgijson/tests/json_converters/functionality/test_collection_support.py
hgijson/tests/json_converters/functionality/test_no_property_access.py
hgijson/tests/json_converters/functionality/test_parent_json_properties.py