Metadata-Version: 1.1
Name: hgijson
Version: 3.1.0
Summary: Python 3 library for easily JSON encoding/decoding complex class-based Python models, using an arbitrarily complex (but easy to write!) mapping schema.
Home-page: https://github.com/wtsi-hgi/python-json
Author: Colin Nolan
Author-email: colin.nolan@sanger.ac.uk
License: MIT
Keywords: json,serialization
Platform: UNKNOWN
Classifier: Development Status :: 5 - Production/Stable
Classifier: Intended Audience :: Developers
Classifier: Operating System :: OS Independent
Classifier: Programming Language :: Python :: 3
Classifier: License :: OSI Approved :: MIT License
